duke_sentry.py
django_duke_sentry-0.1.0.dist-info/METADATA
django_duke_sentry-0.1.0.dist-info/WHEEL
django_duke_sentry-0.1.0.dist-info/entry_points.txt
django_duke_sentry-0.1.0.dist-info/RECORD
