Metadata-Version: 2.1
Name: django-duke-sentry
Version: 0.1.0
Summary: 
Author: Arkadiusz Adamski
Author-email: arkadiusz.adamski@gmail.com
Requires-Python: >=3.11,<4.0
Classifier: Programming Language :: Python :: 3
Classifier: Programming Language :: Python :: 3.11
Classifier: Programming Language :: Python :: 3.12
Requires-Dist: django-configurations (>=2.5,<3.0)
Requires-Dist: django-duke
Requires-Dist: sentry-sdk[django] (>=1.39.2,<2.0.0)
